cdp_backend/__init__.py
cdp_backend/py.typed
cdp_backend/annotation/__init__.py
cdp_backend/annotation/speaker_labels.py
cdp_backend/bin/__init__.py
cdp_backend/bin/add_content_hash_to_sessions.py
cdp_backend/bin/clean_cdp_database.py
cdp_backend/bin/clean_cdp_filestore.py
cdp_backend/bin/create_cdp_database_uml.py
cdp_backend/bin/create_cdp_ingestion_models_doc.py
cdp_backend/bin/create_cdp_transcript_model_doc.py
cdp_backend/bin/get_cdp_infrastructure_stack.py
cdp_backend/bin/process_cdp_event_index_chunk.py
cdp_backend/bin/process_special_event.py
cdp_backend/bin/run_cdp_event_gather.py
cdp_backend/bin/run_cdp_event_index_generation.py
cdp_backend/bin/search_cdp_events.py
cdp_backend/bin/store_cdp_metadata_document.py
cdp_backend/database/__init__.py
cdp_backend/database/constants.py
cdp_backend/database/functions.py
cdp_backend/database/models.py
cdp_backend/database/types.py
cdp_backend/database/validators.py
cdp_backend/file_store/__init__.py
cdp_backend/file_store/functions.py
cdp_backend/infrastructure/Justfile
cdp_backend/infrastructure/__init__.py
cdp_backend/infrastructure/cors.json
cdp_backend/infrastructure/dev-cookiecutter-metadata.yaml
cdp_backend/infrastructure/firebase.json
cdp_backend/infrastructure/firestore.rules
cdp_backend/infrastructure/lifecycle-rules.json
cdp_backend/infrastructure/storage.rules
cdp_backend/infrastructure/gcloud-functions/README.md
cdp_backend/infrastructure/gcloud-functions/generate-clip/.gcloudignore
cdp_backend/infrastructure/gcloud-functions/generate-clip/main.py
cdp_backend/infrastructure/gcloud-functions/generate-clip/requirements.txt
cdp_backend/infrastructure/gcloud-functions/generate-clip/test_empty.py
cdp_backend/pipeline/__init__.py
cdp_backend/pipeline/event_gather_pipeline.py
cdp_backend/pipeline/generate_event_index_pipeline.py
cdp_backend/pipeline/ingestion_models.py
cdp_backend/pipeline/mock_get_events.py
cdp_backend/pipeline/pipeline_config.py
cdp_backend/pipeline/process_event_index_chunk_pipeline.py
cdp_backend-4.1.3.dist-info/LICENSE
cdp_backend-4.1.3.dist-info/METADATA
cdp_backend-4.1.3.dist-info/WHEEL
cdp_backend-4.1.3.dist-info/entry_points.txt
cdp_backend-4.1.3.dist-info/top_level.txt
cdp_backend-4.1.3.dist-info/RECORD
