Metadata-Version: 2.1
Name: cdp-backend
Version: 4.1.3
Summary: Data storage utilities and processing pipelines used by CDP instances.
Author: To Huynh, Isaac Na, Council Data Project Contributors
Author-email: Eva Maxfield Brown <evamaxfieldbrown@gmail.com>
License: MIT License
Project-URL: Homepage, https://github.com/CouncilDataProject/cdp-backend
Project-URL: Bug Tracker, https://github.com/CouncilDataProject/cdp-backend/issues
Project-URL: Documentation, https://CouncilDataProject.github.io/cdp-backend
Project-URL: User Support, https://github.com/CouncilDataProject/cdp-backend/issues
Keywords: civic technology,open government
Classifier: Development Status :: 5 - Production/Stable
Classifier: Intended Audience :: Developers
Classifier: License :: OSI Approved :: MIT License
Classifier: Natural Language :: English
Classifier: Programming Language :: Python :: 3.8
Classifier: Programming Language :: Python :: 3.9
Classifier: Programming Language :: Python :: 3.10
Classifier: Programming Language :: Python :: 3.11
Requires-Python: >=3.8
License-File: LICENSE
Requires-Dist: aiohttp>=3.8.1
Requires-Dist: backoff>=2.2
Requires-Dist: dataclasses-json>=0.5
Requires-Dist: fireo~=1.5
Requires-Dist: fsspec
Requires-Dist: gcsfs>=2022.7.1
Requires-Dist: google-cloud-firestore
Requires-Dist: PyYAML>=5.4.1
Requires-Dist: requests>=2.26.0
Provides-Extra: pipeline
Requires-Dist: dask[distributed]>=2021.7.0; extra == "pipeline"
Requires-Dist: faster-whisper==0.3.0; extra == "pipeline"
Requires-Dist: ffmpeg-python>=0.2.0; extra == "pipeline"
Requires-Dist: graphviz>=0.16; extra == "pipeline"
Requires-Dist: imageio>=2.18; extra == "pipeline"
Requires-Dist: imageio-ffmpeg>=0.4; extra == "pipeline"
Requires-Dist: m3u8-To-MP4==0.1.10; extra == "pipeline"
Requires-Dist: nltk>=3.6; extra == "pipeline"
Requires-Dist: numpy>=1.0; extra == "pipeline"
Requires-Dist: pandas>=1.2; extra == "pipeline"
Requires-Dist: prefect<2,>=1.2; extra == "pipeline"
Requires-Dist: pyarrow>=8.0; extra == "pipeline"
Requires-Dist: pydub>=0.25.1; extra == "pipeline"
Requires-Dist: pypdf>=2.0; extra == "pipeline"
Requires-Dist: rapidfuzz>=2.0; extra == "pipeline"
Requires-Dist: spacy>=3.4; extra == "pipeline"
Requires-Dist: tika==2.6.0; extra == "pipeline"
Requires-Dist: torch<2,>=1.10; extra == "pipeline"
Requires-Dist: tqdm>=4.62; extra == "pipeline"
Requires-Dist: transformers>=4.16; extra == "pipeline"
Requires-Dist: vimeo_downloader>=0.4; extra == "pipeline"
Requires-Dist: yt-dlp>=2023.2.17; extra == "pipeline"
Provides-Extra: functions
Requires-Dist: flask==2.1.0; extra == "functions"
Requires-Dist: functions-framework==3.1.0; extra == "functions"
Requires-Dist: ffmpeg-python==0.2.0; extra == "functions"
Provides-Extra: lint
Requires-Dist: black>=22.3.0; extra == "lint"
Requires-Dist: check-manifest>=0.48; extra == "lint"
Requires-Dist: ruff>=0.0.216; extra == "lint"
Requires-Dist: mypy>=0.790; extra == "lint"
Requires-Dist: pre-commit>=2.20.0; extra == "lint"
Requires-Dist: types-requests>=2.28.5; extra == "lint"
Requires-Dist: types-pytz>=2022.1.2; extra == "lint"
Requires-Dist: types-PyYAML>=6.0.11; extra == "lint"
Provides-Extra: test
Requires-Dist: coverage>=5.1; extra == "test"
Requires-Dist: pytest>=5.4.3; extra == "test"
Requires-Dist: pytest-cov>=2.9.0; extra == "test"
Requires-Dist: pytest-raises>=0.11; extra == "test"
Requires-Dist: networkx>=2.5; extra == "test"
Requires-Dist: pydot>=1.4; extra == "test"
Requires-Dist: requests-mock>=1.10.0; extra == "test"
Provides-Extra: docs
Requires-Dist: m2r2>=0.2.7; extra == "docs"
Requires-Dist: Sphinx>=4.0.0; extra == "docs"
Requires-Dist: furo>=2022.4.7; extra == "docs"
Requires-Dist: numpydoc; extra == "docs"
Requires-Dist: sphinx-copybutton; extra == "docs"
Requires-Dist: docutils<0.19,>=0.18; extra == "docs"
Provides-Extra: dev
Requires-Dist: bokeh; extra == "dev"
Requires-Dist: ipython>=8.4.0; extra == "dev"
